Metadata-Version: 2.1
Name: Udemy-Pythonlib
Version: 1.1.1.2
Summary: Interaja com a plataforma Udemy de forma mais prática para obter detalhes e extrair informações dos cursos em que você está inscrito.
Author: Paulocesar0073
Author-email: pauloguitarrasoms@icloud.com
License: MIT License
Keywords: udemy,apis,udemy downloader,baixar videos udemy
License-File: LICENSE
